{"paths":{"0":["AudioClip/bg",0],"1":["AudioClip/click",0],"2":["AudioClip/win",0],"3":["Font/Arial",1],"4":["Font/BMJZ",1],"5":["Font/FZ",1],"6":["Font/HYZhuZiMuTouRenW",1],"7":["frames/block/H2_0",3],"8":["frames/block/H2_1",3],"9":["frames/block/H3_0",3],"10":["frames/block/H3_1",3],"11":["frames/block/V2_0",3],"12":["frames/block/V2_1",3],"13":["frames/block/V3_0",3],"14":["frames/block/V3_1",3],"15":["frames/Fish",3],"16":["shop/adorn_1",3],"17":["shop/adorn_2",3],"18":["shop/adorn_3",3],"19":["shop/adorn_4",3],"20":["shop/adorn_5",3],"21":["shop/adorn_6",3],"22":["shop/scene_1",3],"23":["shop/scene_2",3],"24":["shop/scene_3",3],"25":["shop/scene_4",3],"26":["shop/scene_5",3],"27":["shop/scene_6",3],"28":["shop/skylark_1",3],"29":["shop/skylark_2",3],"30":["shop/skylark_3",3],"31":["shop/special_1",3],"32":["shop/special_2",3],"33":["shop/special_3",3],"34":["shop/special_4",3],"35":["animation/birdFly",2],"36":["animation/boatShake",2],"37":["animation/fishMove",2],"38":["animation/flowerShake",2],"39":["animation/frogCry",2],"40":["animation/lanternShake",2],"41":["frames/block/H2_0",4,1],"42":["frames/block/H2_1",4,1],"43":["frames/block/H3_0",4,1],"44":["frames/block/H3_1",4,1],"45":["frames/block/V2_0",4,1],"46":["frames/block/V2_1",4,1],"47":["frames/block/V3_0",4,1],"48":["frames/block/V3_1",4,1],"49":["frames/Fish",4,1],"50":["json/level_table",5],"51":["json/shop_table",5],"52":["json/signIn_table",5],"53":["json/words_table",5],"54":["prefab/arrowAnim",6],"55":["prefab/blocks/bird",6],"56":["prefab/blocks/H2",6],"57":["prefab/blocks/H3",6],"58":["prefab/blocks/V2",6],"59":["prefab/blocks/V3",6],"60":["prefab/Circle",6],"61":["prefab/goods",6],"62":["prefab/grade",6],"63":["prefab/layers/addCoinLayer",6],"64":["prefab/layers/fightLayer",6],"65":["prefab/layers/hintLayer",6],"66":["prefab/layers/mainLayer",6],"67":["prefab/layers/overLayer",6],"68":["prefab/layers/selectLayer",6],"69":["prefab/layers/settingLayer",6],"70":["prefab/layers/shopLayer",6],"71":["prefab/layers/signInLayer",6],"72":["prefab/layers/tryOutSkin",6],"73":["prefab/signIn_day1_6",6],"74":["prefab/signIn_day7",6],"75":["shop/adorn_1",4,1],"76":["shop/adorn_2",4,1],"77":["shop/adorn_3",4,1],"78":["shop/adorn_4",4,1],"79":["shop/adorn_5",4,1],"80":["shop/adorn_6",4,1],"81":["shop/scene_1",4,1],"82":["shop/scene_2",4,1],"83":["shop/scene_3",4,1],"84":["shop/scene_4",4,1],"85":["shop/scene_5",4,1],"86":["shop/scene_6",4,1],"87":["shop/skylark_1",4,1],"88":["shop/skylark_2",4,1],"89":["shop/skylark_3",4,1],"90":["shop/special_1",4,1],"91":["shop/special_2",4,1],"92":["shop/special_3",4,1],"93":["shop/special_4",4,1]},"types":["cc.AudioClip","cc.TTFFont","cc.AnimationClip","cc.Texture2D","cc.SpriteFrame","cc.JsonAsset","cc.Prefab"],"uuids":["9ehDZN5W5Hg5U++4iUklDb","8bd5F7wnhEdZLYxAb2NqxO","0bG2z+YUhCqKv6c0fNL9Lk","8dSYnF06JLZ6p2J5olhgHk","e81WhhMYBET7yQc+UCOOXJ","31uiV67xhFsb4Sa532NK9V","bfN+Jg2hNBB6vyopV0S+Dt","12kIGyzVpAEZy81VkeCDv9","9f+RGGmx9IFpCerPgcJ6Wf","dbDnjPD9dPx44X4pSq+rI2","49trQDrUNPJZe5LyEOIs84","74oIm+P5RPgKJWbhloC4lf","00gjFJc6FMYrl+vHViWDzR","b0DCyu74FNIpOcBILj3oy/","d7r9Ur9eBHvoua2sr+o5TF","620ZbCQjhCMazFErn74Mtn","7fpRQWr7hG+o8eUTYkKEX5","d6pUUDl9dNi4S5WGwdZvxG","7dFyGl8HxIhLBr5hH7lksX","9aO4JdZZBN9YKcYG4l+TaQ","00Hku5j/1Mb7acvA2KnH0f","4ddsS4yvFMmZggR+XqtsVQ","ccassLWQRD2Yqh7xCiEDPz","76xxW9TChK+5u7s5fWRiJy","1aXOWFSIZHk46fwE0mrlnY","4eS8z4NoNFQ5ZFFgAVYDJ/","38ZHoT55hHYoMMkX7WgB/+","e3R/CpHWBC+7f9T23VCc36","3dHRY8Ap9P8rQ9HaHM1DFi","f9mCrnejdKLrfu+F2HQqpa","f6R7dvrDRPlpm7KHerKl5n","40nUE/HypLhr5Ag4ml5KFW","17CvQ1bsVNzYOZzP8BuPoB","9aQJ3T2I9JS5k1vAQ8GL+q","76P/tbKrVBkpGezVhQtIlH","eeMtIWXvVPpr5cYafGWUbr","95n8kOvVFIKb3RosGNRtAx","1buhGvlsRM9LPoIlZrXaqz","51xvdIZDJMg5fGbyJiWBdz","2bQfh6rrFNcoNRA8LWfVR4","5eBci2H+NC6YrLycIzEAGO","9bIi3h1adJMp4S0iu7CwJs","55AeHALYlOCLdqdVf9r1h0","ba6V4jSChGL53COi7qgw1V","154Zb7wcREf41wEFd9cAVq","75WOV05LxL7oDyGuzyNMvt","9e/JjWjZNH0oV5KkdOfnM0","5bNTT4TYpIV6gTE5GjDkQd","f6ect+dnNNIqwHG2Q+Io6f","3cZ+q+EkZD7LoYRIfqHZrI","2c22MJUlNEIrn3M1nm74NP","a3iGoHi1dNhq1LSrxrcp3d","ed6Ro8BNhNVb93wC4jlF+q","26wUR2HDRADbk0avqW+TTx","23KGcEpv9G7LpGKXNI7mYY","2986HSAvpGWJXMYfFyTV8c","04b/okeYtDoKDueury1uOY","bfb3+0CU1PXZwx42ylvTtC","3aZ59eGS5ICpnnl9NLsKm8","21lGNEkDdEWoVQNPjyPF46","65cDLu+JNMUIehspxGX5s6","feLcbt9IdDsYGj3D+f8tT/","5e0GW7jZ9IB5uz4QoN8G+N","a62A+bqWZASbvsu6NCn4Dr","f7sPHZ4Q1FBLBsHOU5ul8b","e2BMpuDn1AsIIyH5ceB111","4beb5BeJRIBJ19Mv1vt3hC","77kVs+smpMiKXWAaU1SgFV","27K+G/dexKqKz/fLtY6qRB","780P+Duo5L4q9Krg3KpJuX","8czETECXFCirtimSdjEbFn","6axW/k2wlGSoiOsTxjvgTa","0aZ2zOkbtKxIgC3LuZVZie","b9rtbtjJBAHrN/gDLibEcs","96RoT6yGRC4bV+SmYdTw6c","c7ffL98F1Lfbn2wXjO5FC3","cfFIe079lMNZvPvs14oIql","10QlfsNCZDMK2Be8YLp0/T","a5tQNCCNFFuIEXfqjUr2T2","8cIBKJ61FADa8drQqKxntC","3c4KMzuplA9pVSax8dC4Ar","61Elqfk5FDjYgHeyZsJBQt","eak3+8c/tBpoG00A7WLmPA","eaIofEhTpCGIB9c8NTSsSx","7dHtIOnc5H3qXw/mR7S0tO","acndOWHz1E1KHWTPL4BOlm","a3vDvxHjhNGqLRm8Axf+BK","037aBUWU9JaoMdCKiuae3m","76DdEEIKlJlqiLNR2mTSXP","352VkXSH5Gm4y5e+qHIn0N","16feYbZ8RBTKIa6jk3VDvH","4acDYt069E9qN2PO9PMsIC","35ai9s/C9LTKrcdWV59IOT","55hNziiatN0Ynf6CQz5d37","b2aHrECZ5APKGS/0d2hvT1","3fwNxQf7hJqoOdWxTdRLnG","7b+CfqEAhGEJlce1ETuF9x","4643GacqxDdbzIov0fmmUE","45LjDvPExO7KWdY1F7HsjC","8b6Sr2T2dGC46goXwG+3yJ","5b6uOTnHFGJJIFLWpb85Th","b1qiENLD5NZLxuEhbngriz","1an+JAxgVIDaEZ5X4h/amI","b5PTwyHcRA9rwfl+iOUj5w","f1ha9R1/pF/Ln6PPI58GpB","c6Jmc2CktJHYDFbBjZmQTn","6ekp64WcdBHKvnAcS8Bo+K","f64IOW44xLuILEH55wmoqo","c2JKPIhQ1PPouZ+CFROs6R","2ea8Phmm5G97nboD9/9uCn","3dK6KoQ1xLt6fHjbdD6u7+","99hQMPflVKCKdNs9tHZBx3","c77W/F/LdIjorgtDDI/uiY","97GP9+9PJMnKTGmQmagVRx","b6LayZqoVGBaRMIVcMyIL1","14uwlPfsBEHpFx7wsa+rck","e7rgKzpopKebY1utCfH9Rl","30gV9JmZZKwZnpIYLF0IiJ","c566c1rKdK473pKxayzuRS","c22J37q79HyIcHZDCFFSEM","09bTWJacBAE6Wir1a1hd5j","23J2MTfrdFNpEOish9unZT","73PjwHWj9PL7coABMZ16Mt","fflO8oUe1O6JgZTJwcyNp5","c5BO8kuh5Gu4TNpVarY8lj","45sE+cjE1I1JDHt48OuZPf","11iAickvNP7qsjfXhs00Ub","63Et7khCJEabgJiXwM+2kr","80at6wMuJDObKPrIoi8VNM","36i6IPcwVE/q55uekplGkb","b2C8nPsVtDEJZiNCO4YMeA","f3xhllScdKhrVI51XvXGHe","01ETBDR1tH9qmyJtwOZQ8J","743efXmOZKcJXCMtBvy6A4","cdKLWKBUFIVarYXXAhuKAT","61W8GkYtFBurTy0BKmRB8B","c8S4MWJfRLSr3FEZ0K//5D","d8DAC+WKVN6qxM0qRch0MY","32CYCZZXBNLqQZpDm3kt9V","888d+3DJVKi4vFVsYYhl9N","eeVB2Agu1F6qQG1t9nue7K","bb2Tf4ucBNXLadjcu4dk1/","720HqrEFVJs7eTITPeAug/","13rhlk7nJHybGP3sNagsY7","a5hn7v0+5Iga8uLqWW241I","48e1Ft56FB6I5viqceXmAm","c9JmkP2ydKpIumi/YSfjsu","7d/y7qIcxDg5IKhIJoLjMS","723VWuwpJLb7kNnEQ2wdeA","7eF1YHZORL0Krx9BvLEzNp","3fS1uGrPZGTq2gbq/hgFet","1deTYvZVdBN6Rh7Tuee74s","99yeH+1n5NBI1y0Ux/Kadf","8fqtb4bxBBIK2+oe4C6klh","124t7Ac0BP6IXmaSZzzLQk","edW72vmYpEHLTJ1aRETAXP","e0y3ZsCFtF64myeoY+CBfG","22cs8R7Q9Bl6Zjezjzhy5T","28SL+vbnxCELrbCkpm65/r","f9rv876WlB7KsTAEAwmgld","825J7Pa0tLdrIsGuO0Yj2q","e96vsdhkpGlKsvmjL50LIu","58cL+6PwdJAZ+qg4ITaO+k","789+B8d1VFg5HThdIDyNOq","c7Sd/Gxa9G35VcU9EXAXmV","7a9LRGhQtKya91CUVEBozx","e5lwa9CUdAsKYG9+rFwexa","82nk/8D8RKBZNG6w9TOn1F","b8Hwj4cYJNOLjaIjJLRAZC","918QL+bqxAJIScXdV9b/2J","43bvQ85PhMCrp9iEFma28Z","06vzHF1wxLDLpXpHHser9B","8b/Y3lWa1BYq0DGcfXh1Os","c3yeI1etRLvI8EuKIJ5kdl","5b7yIZy0tBOLLGFTg1HtLC","b6OfrAiHlGOK93wfxM2RSz","ccbLcoYhtNHohMwmpmipBi","5cNUHYWilIkKkwmWtkxOOx","71o4zpfKhBKbT/Sby9kkir","ec4kOk2nREM7iP+0MGFz8G","d0dNHRFl5AQ5xxlUhSlhzx","b4Xb5OLbpO5JV+/pe8I7d8","a2lUtattNLOJQyaczSWYDb","36YD+Y+XpADLkv/Uq5WjxY","9324bJkThDgqjwVrJk95eh","a8hhtjdVdIIpaqeCNXwOpu","35MMkYjc1FK40KCG65vRiC","47bHwW+3RI9rNaZyzYT2df","6eK9TKY99Ps4rnYGDmn04n","edwdwVBgpDBbbCT55c0JsU","4b1pbY5wFDFKq8zx4W2/bE","33L6U3LxZOgZwxju42xhDh","7aU7mllMRJKaHOhyKHwGgS","49BAOM6ipFHJTm6xaKK95p","40xzR5QP1HzaqAZgVQNttT","19ONW33j5K34xBZxgd4vim","d3Gr+HE45HPI9Xg1lyfJvX","6bXtKuaAtMnJr0FHfiMPIt","72R7CYbiZOZrxrF9KZ5R8J","2dOH1DKspHfYDt9DN0hMi3","61WCK1iWpD0L+fNt9jQBam","d0qC05vt5GxLaYyB/w3t//","2cAAAvF3dF85kYlejDMlRk","34cOU0DqNNbJuhFI0NPVH+","30c/HORiJFr4HUvCMDMk+1","19cqsfhR9EIrL/x/V/NY0o","cfFZudFjNIyrbYVCPXAG5B","2e8Xwc5bpCELFnI5HKsgwU","b3c9jbJxxN8pq68R7EWeNP","41uL/ZLQNFUpo08D1KR7uo","2axHYyg1dNmbpMhzR/dRN9","cfvTTCT6NCaJ222lIO3knb","d4E++otrBAo4rsf+10PYqb","f1VwWAqjhGbaig9XaoRSdY","8bZl0J3L9DNYhVPGHdmc0c","ecpdLyjvZBwrvm+cedCcQy","a2MjXRFdtLlYQ5ouAFv/+R","ceqzVA8BdHOaWRw2DQMiIc","0fLCnPt6hOB5KKN8mYOFlb","74hyPPpIBNKpP9TvKcG8ZS","f3Aaby8TREEo9GpOf95Jf+","79YlxJ7wdIBZ6TbY8eT5/s","c50t/YOEdA0o26GhYGQeY7","edI5Rv+x9PUq74pNMclYR+","3b+VSCHhpPa4f7hD8OCcZ2","fdR5yfz95F1Z67eKAK/pmS","630ZhlopFE1oibzBw2MjKL","f1j2g7r+lN1a7Wn/q/O4wj","16YtnPofVAA6uz252Ysm89","a0IuJAXlJA1qxRPR/1EnYu","8f6+WoqOlCF4SA36K0QRGx","a5rJsNZNtL3KYETNWl4V41","1dR0ZJ9yFITJobP5O0TkDT","09phJisSNBS6DveRBUErLC","7aYxSkS4dB3Ig0VjzQyQq2","27AaBwHD5JI6j2p4jZhz1m","3dYkatTJNKUZHgfSaKuGAS","b7EN4JQvpDlZ8976lejw9/","63gsKqhihCAp3J/Xdpee85","43tXfS/oFK3Y40tSkR/pGu","18TA9rarxPw5a4Ay7UtLo1","b1/RFDSEtHkpsqhjWGV4Ww","cbfS2f6tZDz4wlZFQPbccr","cbDEwMkexKS5ZTsUy8TdvF","7eWLPXZiRPEIcUk3h6Xxlf","a9cNzGLCZFvIDnzKZ9SKzK","1cItT49XRDnJWhYnIrcJtX","bfy/2IKwVJnZLvq8BAJoKK","88EYl6sZ5Kk6ZQjIYuY8zg","3eA7APE0RJSqqczbzvPzol","d5jKioNuhCCokuEK84uLTX","0eTXLZO51IB73xGAQTyAd1","68EYpfDGJLnJPD+/pbf6cx","88wszZLQhBrbvffQMijjI2","bfzBIj1jBAjIbTPLz4QT4I","f8IkTaC2NOuIxIGAJRg4N8","b2BpWiIOdGYqjDwo0tYQjo","23CHG6fpxEGqIyUsB8mOLW","f5FGDbbZhPzbs2w8cQYObL","5bufAId3JFb5N5OG3Lc6v8","addnBFNh1PwaIFeslG4RWi","fcmaY0BLBK7Jtokz+TzuYJ","34ZRixqqdF0Ku+G74O8trl","e8tr1S6sdKsrKnmCiaWIB1","8e0ocXXiRGBIZZe7xZ/R2S","989N8z4EdFzrJH5NNO22Nk","a0I/DKAXVAsLip8KCb8AZp","56HJzVhQZP1LaxYJ/U75R3","01JfDj6oNIFb3Ba0JIxVZ2","14ys4ZfqdOp740tp/dgM9j","1e52vQ38pNu4DHdsHrzqg5","59y+jO/gpJsYGD4z+XMzDp","4960E1bzRM2IY6ix1mrxMe","439jxMbbpGDoTzVc31ihSs","9fHjr3I1NOJ7Fh2H1hyBGI","5bMUbK+zBOdInu+kM7PY5f","a4oYGUKQFJ/bFWZioi3reN","29/mFWMp9CM54BgU64KW5S","c4dsjU0IxJv53EKgOxoWia","98TGpI6cRNR7RTqGo5Mtnn","20NWIz+UFD/re+BlgrR/91","81YpuFr2dMGo6CMJ2ttA7m","a1U5RdJRFMFL57BdJC9H1X","74S48iEDJC+Ii4XNkWVtCm","c7nq/yd3xCprWCHl2NA+52","23vvasHYhDbYTZMdnRh+Rf","8fU3QsRVtCk5w66Sa5AtMz","a8tBbK/B9JsYkPOLnr6OIM","21mUElWVpEfqba7hlkoqrj","f7/w0WLdREsbCe/dIs+0Nq","5e4EUFZHFBFq/B+4027NMc","1eESFfdoFGs60vZCvHoUbb","0fnS7IMclB26SwdSGkn3qL","d81rGeKHpBiJfPGBIS+U/y","e57u8UO0tKPKnw55lNkSfL","62kAxUXf1JtrUxzO8gWKFV","e27gWFoiNJL7nfKlZMlDBC","45UakB+CdCnaTY1gLYV3FY","9cEMDVncZC/bWyfyNDL0C6","d4TVoYNjFCq7c0Or2DunR4","33TQ8T9vREWIetTZeJEbDW","734YWNRlRLebTqexkBfa68","23ZLJwym9NS5P0lbsZsGFw","db0qE0Z/1CSIM1MziH433Q","08ihM4UuFCQ6FrKFjSvMXj","c1Yun/Xt1EnosB0qSHbURz","cdde/mltVNA5GOWzAP6Xxr","ccg4sRFUdObZMUnhnt4Z/M","66+BE8z+ZNyaRW2W5Y1Pqw","94tjTNKmZEbrckywBOQoFw","4dEcXl5i1DmrVEKBSd2Xya","02delMVqdBD70a/HSD99FK","47LfXTNedBhJ5sf0G+5l7j"],"scenes":{},"redirect":[215,0,282,0,311,0],"deps":["internal"],"packs":{"0a1fd4c6e":[55,49],"01b4734f5":[54,202],"058e13e03":[44,57],"0de4c3a00":[58,45],"0b99eca7e":[59,48],"077d9eedc":[56,41],"08289061b":[60,208],"0199e5643":[214,211,212,213,61],"09be220d6":[205,207,204,203,62,206],"07745bac4":[262,267,264,265,63,263],"05e415329":[233,251,218,228,240,37,232,257,235,39,224,236,239,312,91,38,259,40,238,226,252,219,221,234,244,253,230,36,229,231,245,260,241,94,237,254,222,243,242,217,223,35,227,220,258,64,225],"0dae9c6cc":[246,249,248,256,247],"0ef016160":[269,270,273,272,66,271,275,274,276],"0f691da8d":[280,277,67,281,279,278],"06266e9bb":[285,68,283,284],"01960bf20":[292,291,288,290,69,287,293,294,289],"0426f06dd":[302,300,297,295,301,70,298,299,296],"06843b75c":[310,71],"0d35c7103":[304,72,303],"0d8e43690":[309,73],"08ead640c":[308,74,307,306],"02e6b7038":[20,12,132,171,120,126,7,154,143,115,32,195,24,102,151,157,121,158,199,109,117,138,191,186,183,129,26,28,110,150,95,31,194,170,98,125,97,187,145,193,10,190,21,25,162,100,174,177,200,135,15,127,197,188,106,178,198,142,148,122,11,133,34,23,163,192,165,96,18,147,149,16,128,167,160,139,99,172,153,169,184,113,111,152,19,33,8,182,144,185,13,101,130,181,103,114,175,168,141,108,119,173,124,118,105,164,112,136,146,22,176,134,180,201,196,17,14,137,9,156,27,166,116,161,179,155,189,140,104,131,30,107,29,159,123]},"name":"resources","importBase":"import","nativeBase":"native","debug":false,"isZip":false,"encrypted":false,"versions":{"import":[268,"12d1f","01960bf20","68486","0199e5643","7cf1e","01b4734f5","22b74","02e6b7038","870a8",87,"add4c","0426f06dd","80547","058e13e03","84db7","05e415329","bf335","06266e9bb","8cb6a","06843b75c","4a9a1","07745bac4","1b846","077d9eedc","348f6","08289061b","3ef22","08ead640c","ffe2a","09be220d6","618e4","0a1fd4c6e","f353f",2,"57c02","0b99eca7e","02cd6","0d35c7103","eb4cf","0d8e43690","10cfd","0dae9c6cc","aabcc","0de4c3a00","b5f26","0ef016160","e774b","0f691da8d","03328",77,"35d0a",90,"13bf0",53,"1da6d",210,"c2e85",50,"14413",5,"4eab3",92,"e1510",89,"a6a77",80,"fe77e",209,"448c8",42,"b06f9",93,"5168d",47,"2098c",81,"1d1cc",88,"6f049",84,"89394",1,"b66c3",79,"b2ff4",3,"d5b04",286,"3122a",0,"17ddc",46,"188bc",266,"3348f",216,"43d76",51,"d09c7",86,"8eb0e",78,"05858",85,"03762",43,"8f93d",6,"392f7",305,"4358e",75,"bea7f",76,"1131c",250,"d45a1",65,"5a6a5",4,"2af0a",83,"1a10f",82,"b5caa",52,"1724e",255,"01de3",261,"28853"],"native":[20,"b2dce",12,"a60f6",132,"2d649",171,"086f3",120,"078c0",2,"0f1cc",126,"21c69",7,"3f484",154,"6192f",143,"19f68",115,"1a3fa",32,"6636c",195,"2548c",24,"92281",102,"1231d",151,"f96bd",157,"62974",121,"d46f6",158,"6867f",199,"c47c7",109,"f0b53",117,"daa99",5,"6a3ff",138,"34cb3",191,"c8170",186,"44da0",183,"19715",129,"6e888",26,"fae75",28,"b41b2",110,"517f9",150,"5bb9f",95,"1d7d5",31,"93d43",194,"e6820",170,"4519d",98,"fc2fd",125,"f7225",97,"f2679",187,"c2fcb",145,"fee13",193,"595a7",10,"45940",190,"519fc",21,"4cc78",25,"102af",162,"f28ce",100,"4b0a6",174,"45690",177,"2de4d",200,"65fbe",135,"6d96a",15,"6d357",127,"e4f5c",197,"1231d",188,"98d10",106,"3b594",178,"bcf2d",198,"0e5e9",142,"9ed11",148,"d1ecc",122,"360da",11,"c0fa7",133,"85b3d",34,"5addc",23,"2548c",163,"f15dd",192,"e1dfd",165,"26895",96,"d7c7c",18,"29efa",147,"5066f",149,"da18d",16,"10003",128,"4ea7d",167,"32af3",160,"c8284",139,"0bc2a",1,"5c271",99,"8886e",172,"7f094",3,"cb92a",153,"21195",169,"96c73",184,"ff626",113,"90d7f",111,"1d510",152,"94360",19,"f4ccc",33,"c0e15",0,"c43ce",8,"83285",182,"49883",144,"6e904",185,"2f76c",13,"490e1",101,"aa7f5",130,"57893",94,"2bf0b",181,"2c716",103,"b0509",114,"2cc78",175,"a674e",168,"5c271",141,"cf604",6,"85dcf",108,"1cb75",119,"d18cb",173,"550f7",124,"6363b",118,"d2497",105,"9e32b",164,"a2a06",112,"24d2f",136,"54a82",146,"e4974",22,"009ba",176,"cdb0d",134,"45af9",180,"e0685",201,"841f5",196,"45621",17,"ec3fa",14,"f99e2",137,"5b3c1",9,"656af",156,"ad307",27,"bf4cf",166,"0fa76",116,"dafa4",4,"3bf59",161,"fb9d2",179,"fb50b",155,"43426",189,"b5293",140,"b8342",104,"d780d",131,"5fd0e",30,"43bd3",107,"3938d",29,"f7ab7",159,"09132",123,"92d25"]}}